brainles_aurora/.gitignore
brainles_aurora/__init__.py
brainles_aurora/inferer/__init__.py
brainles_aurora/inferer/config.py
brainles_aurora/inferer/constants.py
brainles_aurora/inferer/data.py
brainles_aurora/inferer/inferer.py
brainles_aurora/inferer/log_config.json
brainles_aurora/inferer/model.py
brainles_aurora/utils/__init__.py
brainles_aurora/utils/console_decorators.py
brainles_aurora/utils/utils.py
brainles_aurora/utils/weights.py
brainles_aurora-0.2.7.dist-info/LICENSE
brainles_aurora-0.2.7.dist-info/METADATA
brainles_aurora-0.2.7.dist-info/WHEEL
brainles_aurora-0.2.7.dist-info/RECORD
