Metadata-Version: 2.3
Name: brainles_aurora
Version: 0.2.7
Summary: Segmentation models for cancer metastasis in brain MR.
License: Apache-2.0
Author: Florian Kofler
Author-email: florian.kofler@tum.de
Maintainer: Florian Kofler
Maintainer-email: florian.kofler@tum.de
Requires-Python: >=3.8
Classifier: License :: OSI Approved :: Apache Software License
Classifier: License :: OSI Approved :: GNU Affero General Public License v3
Classifier: Operating System :: OS Independent
Classifier: Programming Language :: Python :: 3
Classifier: Programming Language :: Python :: 3.8
Classifier: Programming Language :: Python :: 3.9
Classifier: Programming Language :: Python :: 3.10
Classifier: Programming Language :: Python :: 3.11
Classifier: Programming Language :: Python :: 3.12
Classifier: Programming Language :: Python :: 3.13
Requires-Dist: monai (>=1.2.0)
Requires-Dist: nibabel (>=4.0.2)
Requires-Dist: numpy (>=1.23.0)
Requires-Dist: path (>=16.2.0,<17.0.0)
Requires-Dist: requests (>=2.0.0)
Requires-Dist: rich (>=13.0.0)
Requires-Dist: torch (>=2.1.0)
Requires-Dist: tqdm (>=4.64.1,<5.0.0)
Project-URL: Repository, https://github.com/BrainLesion/AURORA
